[
    {
        "(Q3595028, P1343, Q3595028-57340f4e-4a4b-334c-d053-ef30abdc4f65)": {
            "雨-described by source-Kangxi Dictionary": [
                "The term '雨' is described by the source 'Kangxi Dictionary'.",
                "The source 'Kangxi Dictionary' describes the term '雨'."
            ]
        }
    },
    {
        "(Q3595028, P180, Q3595028-0417af55-4176-6ba4-145a-2f02a83e2567)": {
            "雨-depicts-rain": [
                "'雨' depicts 'rain'.",
                "'雨' is a representation of 'rain'."
            ]
        }
    },
    {
        "(Q3595028, P282, Q3595028-62c3c21d-4a67-669f-8973-e7b8d8a3a43f)": {
            "雨-writing system-chữ Nôm": [
                "'雨' uses the 'chữ Nôm' writing system.",
                "The writing system for '雨' is 'chữ Nôm'."
            ]
        },
        "(Q3595028, P282, Q3595028-d5dd9b0d-4593-c07e-0c99-58eafe04206c)": {
            "雨-writing system-kanji": [
                "'雨' uses the 'kanji' writing system.",
                "The writing system for '雨' is 'kanji'."
            ]
        },
        "(Q3595028, P282, Q3595028-f49c1f49-4965-1748-3205-b37bf082e0c3)": {
            "雨-writing system-Hanja": [
                "'雨' uses the 'Hanja' writing system.",
                "The writing system for '雨' is 'Hanja'."
            ]
        }
    },
    {
        "(Q3595028, P31, Q3595028-06DD95F5-48BD-4FBC-9D5C-2A94DFED6290)": {
            "雨-instance of-Unicode character-:follows-雧:followed by-雩": [
                "'雨' is an instance of 'Unicode character', which follows '雧' and is followed by '雩'.",
                "'雨' is a 'Unicode character' that comes after '雧' and before '雩'."
            ]
        },
        "(Q3595028, P31, Q3595028-742275E4-8E53-4042-90B2-6C354C456108)": {
            "雨-instance of-Chinese character": [
                "'雨' is an instance of 'Chinese character'.",
                "'雨' is a 'Chinese character'."
            ]
        },
        "(Q3595028, P31, Q3595028-8A4FAF91-10F7-4DED-BF1E-0D20E9B9BF28)": {
            "雨-instance of-CJK character": [
                "'雨' is an instance of 'CJK character'.",
                "'雨' is a 'CJK character'."
            ]
        },
        "(Q3595028, P31, Q3595028-8df9ce50-4b7c-0668-755a-1261bc5b3c83)": {
            "雨-instance of-pictogram": [
                "'雨' is an instance of 'pictogram'.",
                "'雨' is a 'pictogram'."
            ]
        }
    },
    {
        "(Q3595028, P5205, Q3595028-1622C60B-9674-43E3-ABD2-FBA55CE68A4C)": {
            "雨-stroke count-8": [
                "The stroke count of '雨' is 8.",
                "One writes '雨' using 8 strokes."
            ]
        }
    },
    {
        "(Q3595028, P5523, Q3595028-36dd6a73-4570-890a-bb26-f629228c85c7)": {
            "雨-fanqie-遇": [
                "The character '雨' has a fanqie spelling represented by the character '遇'.",
                "In fanqie, '遇' represents the character '雨'."
            ]
        },
        "(Q3595028, P5523, Q3595028-39584a2f-4ba6-4bb3-ecc4-c78f13c2ab76)": {
            "雨-fanqie-矩": [
                "The fanqie spelling of the character '雨' is represented by '矩'.",
                "'矩' represents the character '雨' in fanqie spelling."
            ]
        },
        "(Q3595028, P5523, Q3595028-90d86432-4dd5-01eb-805d-c90a88f0e0a7)": {
            "雨-fanqie-王": [
                "'王' represents the fanqie spelling of the character '雨'.",
                "The character '雨' is spelled as '王' in fanqie."
            ]
        },
        "(Q3595028, P5523, Q3595028-d44b7f28-4db6-d008-6000-712219626ff3)": {
            "雨-fanqie-王": [
                "'雨' is represented by '王' in fanqie spelling.",
                "In fanqie, the character '雨' is spelled as '王'."
            ]
        }
    },
    {
        "(Q3595028, P5537, Q3595028-947b936f-47de-a59e-7883-b85387340444)": {
            "雨-Hangul-우": [
                "'우' is the Hangul for '雨'.",
                "The Hangul of the Chinese character '雨' is '우'."
            ]
        }
    },
    {
        "(Q3595028, P972, Q3595028-19e09e7b-4377-11a2-670e-3d0d7965df22)": {
            "雨-catalog-Table of General Standard Chinese Characters": [
                "The Chinese character '雨' is listed in the 'Table of General Standard Chinese Characters' catalog.",
                "'雨' is included in the catalog of 'Table of General Standard Chinese Characters'."
            ]
        }
    },
    {
        "(Q3392, P1343, Q3392-44428FC2-62E9-4882-B642-8002D90BF045)": {
            "Nile-described by source-Brockhaus and Efron Encyclopedic Dictionary": [
                "The Nile is described by the source 'Brockhaus and Efron Encyclopedic Dictionary'.",
                "'Brockhaus and Efron Encyclopedic Dictionary' provides a description of the Nile."
            ]
        }
    },
    {
        "(Q3392, P17, Q3392-28687abf-4d1b-3480-b979-bcf21994870f)": {
            "Nile-country-Tanzania": [
                "The country of the Nile is Tanzania.",
                "The Nile runs through Tanzania."
            ]
        }
    },
    {
        "(Q3392, P1889, Q3392-86FBB569-B2FB-41FA-A52F-3FF93082A7D0)": {
            "Nile-different from-Nil": [
                "The Nile is different from Nil.",
                "The Nile shouldn't be confused with Nil."
            ]
        }
    },
    {
        "(Q3392, P2043, Q3392-2a0f0e27-4d98-2522-d7eb-5c3f64797e26)": {
            "Nile-length-6650:references work, tradition or theory-Encyclopædia Britannica-kilometre": [
                "The length of the Nile is 6650 kilometres according to the Encyclopædia Britannica.",
                "According to the Encyclopædia Britannica, the Nile stretches 6650 kilometres."
            ]
        },
        "(Q3392, P2043, Q3392-50110dc8-4b1f-05ec-445e-1605e6f54154)": {
            "Nile-length-6690:applies to part-drainage system-kilometre": [
                "The length of the Nile's drainage system is 6690 kilometres.",
                "The drainage system of the Nile extends for 6690 kilometres."
            ]
        },
        "(Q3392, P2043, Q3392-73ab6652-4dda-3fc0-86f7-5024e400f6c2)": {
            "Nile-length-2850:kilometre": [
                "The length of the Nile is 2850 kilometres.",
                "The Nile stretches 2850 kilometres in length."
            ]
        }
    },
    {
        "(Q3392, P2044, Q3392-1B77C2AB-4FC6-4EE9-A9DD-18D9A9111BB7)": {
            "Nile-elevation above sea level-2700:applies to part-White Nile-metre": [
                "The elevation of the Nile at the White Nile is 2700 metres above sea level.",
                "At the White Nile, the Nile's elevation is 2700 metres above sea level."
            ]
        },
        "(Q3392, P2044, Q3392-369d6ad1-4db9-cf0c-5382-01ab14a2f410)": {
            "Nile-elevation above sea level-0:applies to part-river mouth-metre": [
                "The elevation of the Nile at the river mouth is 0 metres above sea level.",
                "The river mouth of the Nile is at sea level."
            ]
        }
    },
    {
        "(Q3392, P205, Q3392-06F0B3E5-A92A-461F-8FB0-B468662A2D14)": {
            "Nile-basin country-Eritrea": [
                "The Nile basin includes Eritrea.",
                "Eritrea is a part of the Nile basin.",
                "The Nile runs through Eritrea.",
                "The Nile passes through Eritrea",
                "The Nile passes go Eritrea"
            ]
        }
    },
    {
        "(Q3392, P2053, Q3392-336A2F2C-9B35-498D-AB33-E27CC908CFB8)": {
            "Nile-watershed area-3400000:square kilometre": [
                "The watershed area of the Nile is 3,400,000 square kilometres.",
                "The Nile has a watershed area of 3,400,000 square kilometres."
            ]
        }
    },
    {
        "(Q3392, P2225, Q3392-dff97ec2-4c0f-6a4b-6351-f00c887a4276)": {
            "Nile-discharge-2830:cubic metre per second": [
                "The discharge of the Nile is 2830 cubic metres per second.",
                "The Nile discharge rate is 2830 cubic metres per second."
            ]
        }
    },
    {
        "(Q3392, P30, Q3392-FD5B8495-2811-4847-8102-7D6B8AF95EDB)": {
            "Nile-continent-Africa": [
                "The continent of the Nile is Africa.",
                "The Nile is located in Africa."
            ]
        }
    },
    {
        "(Q3392, P31, Q3392-54EFC97B-2CCF-4598-BD4F-86DCBB3E5C5F)": {
            "Nile-instance of-river": [
                "The Nile is a river.",
                "-"
            ]
        }
    },
    {
        "(Q3392, P403, Q3392-6F881C7F-7012-4139-8F7E-63D4B264E975)": {
            "Nile-mouth of the watercourse-Mediterranean Sea": [
                "The mouth of the watercourse of the Nile is the Mediterranean Sea.",
                "The Nile discharge into the Mediterranean Sea."
            ]
        }
    },
    {
        "(Q3392, P625, Q3392-328379C0-9B40-44E8-A671-1FE0C5B4A37C)": {
            "Nile-coordinate location-Point(32.5055 15.640138888):applies to part-river source": [
                "The coordinate location of the Nile's source is at the point (32.5055, 15.640138888).",
                "The Nile' source is at (32.5055, 15.640138888)."
            ]
        },
        "(Q3392, P625, Q3392-E103C40D-A968-43D5-9994-C8F68E9EF591)": {
            "Nile-coordinate location-Point(30.3667 31.4653):applies to part-river mouth": [
                "The coordinate location of the Nile's river mouth is at the point (30.3667, 31.4653).",
                "The Nile's mouth is at coordinates (30.3667, 31.4653)."
            ]
        }
    },
    {
        "(Q3392, P885, Q3392-41c25f4b-4865-f705-a719-e6b340e2ec94)": {
            "Nile-origin of the watercourse-Blue Nile": [
                "The origin of the watercourse of the Nile is the Blue Nile.",
                "The Nile starts from the Blue Nile."
            ]
        },
        "(Q3392, P885, Q3392-4b5deb53-4e46-0223-bbe0-fad67fa3af0c)": {
            "Nile-origin of the watercourse-White Nile": [
                "The origin of the watercourse of the Nile is the White Nile.",
                "The Nile starts from the White Nile."
            ]
        }
    },
    {
        "(Q3392, P974, Q3392-71AFDF8B-EEF6-44B2-9218-A45102314D1A)": {
            "Nile-tributary-Atbarah River": [
                "The Atbarah River is a tributary of the Nile.",
                "The Atbarah River discharges into the Nile."
            ]
        },
        "(Q3392, P974, Q3392-BB8151DD-5ED0-41DC-8995-F8F5D7A1F1B3)": {
            "Nile-tributary-Wadi Hammamat": [
                "The Wadi Hammamat is a tributary of the Nile.",
                "The Wadi Hammamat discharges into the Nile."
            ]
        }
    },
    {
        "(Q140, P1034, Q140-231f7732-4c1e-8137-f6b8-30f42b196272)": {
            "lion-main food source-ungulate": [
                "The main food source of a lion is ungulate.",
                "Lions primarily feed on ungulates."
            ]
        }
    },
    {
        "(Q140, P105, Q140-CD2903E5-743A-4B4F-AE9E-9C0C83426B11)": {
            "lion-taxon rank-species": [
                "The taxon rank of a lion is a species.",
                "Lions belong to the taxonomic rank of species."
            ]
        }
    },
    {
        "(Q140, P1343, Q140-100f480e-4ad9-b340-8251-4e875d00315d)": {
            "lion-described by source-The Nuttall Encyclopædia": [
                "The lion is described by the source 'The Nuttall Encyclopædia'.",
                "'The Nuttall Encyclopædia describes the lion."
            ]
        },
        "(Q140, P1343, Q140-8f1079fe-4769-c555-661c-7e9cb369b15e)": {
            "lion-described by source-Armenian Soviet Encyclopedia": [
                "The lion is described by the source 'Armenian Soviet Encyclopedia'.",
                "'Armenian Soviet Encyclopedia describes the lion."
            ]
        },
        "(Q140, P1343, Q140-fde46981-4512-17b5-577b-d2ad433888b5)": {
            "lion-described by source-Internetowa encyklopedia PWN:language of work or name-Polish": [
                "The lion is described by the Polish source 'Internetowa encyklopedia PWN'",
                "The Polish source 'Internetowa encyklopedia PWN' describes the lion.."
            ]
        }
    },
    {
        "(Q140, P1403, Q140-816d2b99-4aa5-5eb9-784b-34e2704d2927)": {
            "lion-original combination-Felis leo": [
                "The original combination of the lion is 'Felis leo'.",
                "The original classification of the lion is 'Felis leo'."
            ]
        }
    },
    {
        "(Q140, P141, Q140-B12A2FD5-692F-4D9A-8FC7-144AA45A16F8)": {
            "lion-IUCN conservation status-Vulnerable": [
                "The IUCN conservation status of the lion is Vulnerable.",
                "Lions is Vulnerable according to the IUCN conservation status."
            ]
        }
    },
    {
        "(Q140, P1552, Q140-0bd4b0d9-49ff-b5b4-5c10-9500bc0ce19d)": {
            "lion-has quality-viviparity": [
                "Lions are viviparous.",
                "-"
            ]
        },
        "(Q140, P1552, Q140-b352a202-4b88-d204-e740-c9083b490398)": {
            "lion-has quality-carnivore": [
                "Lions are carnivorous.",
                "-"
            ]
        }
    },
    {
        "(Q140, P171, Q140-C1CA40D8-39C3-4DB4-B763-207A22796D85)": {
            "lion-parent taxon-Panthera": [
                "The parent taxon of a lion is Panthera.",
                "Lions belong to the Panthera taxon."
            ]
        }
    },
    {
        "(Q140, P2067, Q140-198da244-7e66-4258-9434-537e9ce0ffab)": {
            "lion-mass-1.65 kilograms:of-birth mass": [
                "The birth mass of a lion is 1.65 kilograms.",
                "A newborn lion weighs approximately 1.65 kilograms."
            ]
        },
        "(Q140, P2067, Q140-20d80fe2-4796-23d1-42c2-c103546aa874)": {
            "lion-mass-126 kilograms:sex or gender-female organism": [
                "The female lion mass is 126 kilograms.",
                "Lionesses weighs approximately 126 kilograms."
            ]
        },
        "(Q140, P2067, Q140-a3092626-4295-efb8-bbb6-eed913d02fc7)": {
            "lion-mass-188 kilograms:of-adult weight": [
                "The adult lion mass is 188 kilograms.",
                "Adult lions weighs approximately 188 kilograms."
            ]
        }
    },
    {
        "(Q140, P279, Q140-cb41b7d3-46f0-e6d9-ced6-c2803e0c06b7)": {
            "lion-subclass of-big cat": [
                "The lion is a subclass of big cat.",
                "Lions are a type of big cat."
            ]
        }
    },
    {
        "(Q140, P3063, Q140-878ff87d-40d0-bb2b-c83d-4cef682c2687)": {
            "lion-gestation period-108:day": [
                "The gestation period of a lion is 108 days.",
                "The lion's gestation period of is 108 days."
            ]
        }
    },
    {
        "(Q140, P31, q140-8EE98E5B-4A9C-4BF5-B456-FB77E8EE4E69)": {
            "lion-instance of-taxon": [
                "The lion is an instance of a taxon.",
                "The lion classifies as a type of taxon."
            ]
        }
    },
    {
        "(Q140, P3485, Q140-4B70AA09-AE2F-4F4C-9BAF-09890CDA11B8)": {
            "lion-bite force quotient-112": [
                "The bite force quotient of a lion is 112.",
                "A lion's bite force quotient is 112."
            ]
        }
    },
    {
        "(Q140, P4214, Q140-ec1ccab2-f506-4c81-9179-4625bbbbbe27)": {
            "lion-longest observed lifespan-27:year": [
                "The longest observed lifespan of a lion is 27 years.",
                "The longest observed lion's lifespan is 27 years."
            ]
        }
    },
    {
        "(Q140, P4733, Q140-3773ba15-4723-261a-f9a8-544496938efa)": {
            "lion-produced sound-roar": [
                "The lion produces a sound which is a roar.",
                "The lion's sound is called roar."
            ]
        }
    },
    {
        "(Q140, P7725, Q140-f1f04a23-0d34-484a-9419-78d12958170c)": {
            "lion-litter size-2.5": [
                "The litter size of a lion is 2.5.",
                "The lion's litter size is 2.5."
            ]
        }
    },
    {
        "(Q140, P7862, Q140-17b64a1e-4a13-9e2a-f8a2-a9317890aa53)": {
            "lion-period of lactation-8:month": [
                "The period of lactation for a lion is 8 months.",
                "A lioness typically takes care of her cubs for a period of 8 months."
            ]
        }
    },
    {
        "(Q140, P9566, Q140-C7DAEA4E-B613-48A6-BFCD-88B551D1EF7A)": {
            "lion-diel cycle-crepuscular": [
                "The lion has a crepuscular diel cycle.",
                "Lions are crepuscular."
            ]
        }
    },
    {
        "(Q395, P1343, Q395-23fec3d2-4958-9102-16b9-ee887970b7ed)": {
            "mathematics-described by source-Encyclopædia Britannica 11th edition": [
                "Mathematics is described by the source 'Encyclopædia Britannica 11th edition'.",
                "The 'Encyclopædia Britannica 11th edition' describes mathematics."
            ]
        },
        "(Q395, P1343, Q395-3856e109-4df9-c9ed-631f-b2ee89f69f34)": {
            "mathematics-described by source-Small Brockhaus and Efron Encyclopedic Dictionary": [
                "Mathematics is described by the source 'Small Brockhaus and Efron Encyclopedic Dictionary'.",
                "The 'Small Brockhaus and Efron Encyclopedic Dictionary' describes mathematics."
            ]
        }
    },
    {
        "(Q395, P1552, Q395-9b219fbf-4067-528e-63ce-e6e1fd7552ba)": {
            "mathematics-has quality-eternity:statement supported by-Platonism:nature of statement-disputed:statement is subject of-mathematical realism": [
                "Mathematics is eternity, which is supported by 'Platonism', however, the nature of this statement is disputed and it is the subject of 'mathematical realism'.",
                "-"
            ]
        }
    },
    {
        "(Q395, P2578, Q395-a44183fb-437e-43d1-ea70-3d9c52916ab4)": {
            "mathematics-is the study of-mathematical object": [
                "Mathematics is the study of mathematical objects.",
                "Mathematical objects are the study of mathematics."
            ]
        }
    },
    {
        "(Q395, P279, Q395-4e113cdf-493d-0597-fc2d-3b3f74390d4c)": {
            "mathematics-subclass of-natural science": [
                "Mathematics is a subclass of natural science.",
                "Mathematics is a part of natural science."
            ]
        }
    },
    {
        "(Q395, P3095, Q395-078972ca-48dd-2753-cb3a-002db0645efe)": {
            "mathematics-practiced by-mathematician": [
                "Mathematics is practiced by mathematicians.",
                "People who practice mathematics are called mathematicians."
            ]
        }
    },
    {
        "(Q395, P361, Q395-ae319d5e-45ee-fd47-f0b7-92298c0bc379)": {
            "mathematics-part of-STEM fields": [
                "Mathematics is a part of STEM fields.",
                "STEM fields oncludes Mathematics."
            ]
        },
        "(Q395, P361, Q395-cf2ce2f8-4078-a84f-a5b6-aefca4ede853)": {
            "mathematics-part of-exact science:nature of statement-partially": [
                "Mathematics is partially a part of the exact science.",
                "While mathematics is considered a part of exact science, this statement is only partially true."
            ]
        },
        "(Q395, P361, Q395-f67e8af6-4c43-afd7-7872-83ec6d89f589)": {
            "mathematics-part of-formal science": [
                "Mathematics is a part of formal science.",
                "Formal science includes mathematics."
            ]
        }
    },
    {
        "(Q395, P366, Q395-008d97ad-4044-d267-c2c4-d47b8fef5465)": {
            "mathematics-has use-engineering": [
                "Mathematics is used in engineering.",
                "Engineering uses mathematics."
            ]
        },
        "(Q395, P366, Q395-227eb853-4310-7008-5c03-9b6002761ea1)": {
            "mathematics-has use-mathematical modelling": [
                "Mathematics is used in mathematical modelling.",
                "Mathematical modelling uses mathematics."
            ]
        },
        "(Q395, P366, Q395-2b45301c-415b-822c-9d8c-2a0356e5082e)": {
            "mathematics-has use-computation": [
                "Mathematics is used in computation.",
                "Computation uses mathematics."
            ]
        },
        "(Q395, P366, Q395-5d050628-428e-8c2f-cdc9-15a74143f454)": {
            "mathematics-has use-science": [
                "Mathematics is used in science.",
                "Science uses mathematics."
            ]
        },
        "(Q395, P366, Q395-93d61e3d-42bf-3ddd-7aa0-2a82b06abcec)": {
            "mathematics-has use-finance": [
                "Mathematics is used in finance.",
                "Finance uses mathematics."
            ]
        }
    },
    {
        "(Q9049, Q8162, Q9049-38aae2db-45bb-8fd6-2930-d5d9c33923d3)": {
            "Noam Chomsky-field of work-linguistics": [
                "Noam Chomsky's field of work is linguistics.",
                "Noam Chomsky works in the field of linguistics."
            ]
        },
        "(Q9049, Q147638, Q9049-42acfa21-4fb1-dcaf-bb29-70f4c9236359)": {
            "Noam Chomsky-field of work-cognitive science": [
                "Noam Chomsky's field of work is cognitive science.",
                "Noam Chomsky works in the field of cognitive science."
            ]
        },
        "(Q9049, Q9418, Q9049-642f73c5-4978-8cc8-8aa0-f5cca3f3c770)": {
            "Noam Chomsky-field of work-psychology": [
                "Noam Chomsky's field of work is psychology.",
                "Noam Chomsky works in the field of psychology."
            ]
        },
        "(Q9049, Q23407, Q9049-83fb8e42-4d47-6fc3-dba5-ff1c5fa1780c)": {
            "Noam Chomsky-field of work-philosophy of mind": [
                "Noam Chomsky's field of work is philosophy of mind.",
                "Noam Chomsky works in the field of philosophy of mind."
            ]
        },
        "(Q9049, Q83966, Q9049-8f74063c-453e-30b4-84cd-874236b7bacf)": {
            "Noam Chomsky-field of work-communication theory": [
                "Noam Chomsky's field of work is communication theory.",
                "Noam Chomsky works in the field of communication theory."
            ]
        },
        "(Q9049, Q36108, Q9049-90a55686-4f95-389f-12ed-ff6ac0c098c4)": {
            "Noam Chomsky-field of work-generative grammar": [
                "Noam Chomsky's field of work is generative grammar.",
                "Noam Chomsky works in the field of generative grammar."
            ]
        },
        "(Q9049, Q7163, Q9049-9b59fc1e-42b0-7c95-8f53-0b49e5022529)": {
            "Noam Chomsky-field of work-politics": [
                "Noam Chomsky's field of work is politics.",
                "Noam Chomsky works in the field of politics."
            ]
        },
        "(Q9049, Q484761, Q9049-a29fcfe4-44b4-ea4b-7e3b-bca2214a6100)": {
            "Noam Chomsky-field of work-philosophy of language": [
                "Noam Chomsky's field of work is philosophy of language.",
                "Noam Chomsky works in the field of philosophy of language."
            ]
        },
        "(Q9049, Q9465, Q9049-cd52ee28-40e2-0bad-2318-6aa366e4c658)": {
            "Noam Chomsky-field of work-ethics": [
                "Noam Chomsky's field of work is ethics.",
                "Noam Chomsky works in the field of ethics."
            ]
        }
    },
    {
        "(Q9049, P103, Q9049-f3657451-49d7-910e-eeaf-2658533cd411)": {
            "Noam Chomsky-native language-English": [
                "Noam Chomsky's native language is English.",
                "Noam Chomsky speaks English as his native language."
            ]
        },
        "(Q9049, P103, q9049-3131413B-B5B7-4368-B656-8B23683F6464)": {
            "Noam Chomsky-native language-American English": [
                "Noam Chomsky's native language is American English.",
                "Noam Chomsky speaks American English as his native language."
            ]
        }
    },
    {
        "(Q9049, P106, Q9049-232a4182-10e6-4c16-9713-ce429e491e56)": {
            "Noam Chomsky-occupation-computer scientist": [
                "Noam Chomsky's occupation is a computer scientist.",
                "Noam Chomsky works as a computer scientist."
            ]
        },
        "(Q9049, P106, Q9049-278d127d-4474-5a24-b2df-30a64f2f41ab)": {
            "Noam Chomsky-occupation-political writer": [
                "Noam Chomsky's occupation is a political writer.",
                "Noam Chomsky works as a political writer."
            ]
        }
    },
    {
        "(Q9049, P1066, Q9049-4d95ad1e-41f3-541e-cecf-2a1e9b056eee)": {
            "Noam Chomsky-student of-Roman Jakobson": [
                "Noam Chomsky was a student of Roman Jakobson.",
                "Noam Chomsky studied under Roman Jakobson."
            ]
        },
        "(Q9049, P1066, Q9049-c58a9d17-4557-fe74-f640-5d1de35ffba3)": {
            "Noam Chomsky-student of-Nelson Goodman": [
                "Noam Chomsky was a student of Nelson Goodman.",
                "Noam Chomsky studied under Nelson Goodman."
            ]
        },
        "(Q9049, P1066, Q9049-f3b365f4-4b69-9636-e25a-4f774b5d4b11)": {
            "Noam Chomsky-student of-Zellig S. Harris": [
                "Noam Chomsky was a student of Zellig S. Harris.",
                "Noam Chomsky studied under Zellig S. Harris."
            ]
        }
    },
    {
        "(Q9049, P108, q9049-28F811D8-08A8-4422-A7AC-727B4A5AC698)": {
            "Noam Chomsky-employer-Massachusetts Institute of Technology:position held-professor": [
                "Noam Chomsky's employer is the Massachusetts Institute of Technology where he holds the position of professor.",
                "Noam Chomsky is employed as a professor at the Massachusetts Institute of Technology."
            ]
        }
    },
    {
        "(Q9049, P1142, Q9049-43f20213-4e7a-5072-2747-75904cbf41b4)": {
            "Noam Chomsky-political ideology-antimilitarism": [
                "Noam Chomsky's political ideology is antimilitarism.",
                "Noam Chomsky advocates for an antimilitarism."
            ]
        },
        "(Q9049, P1142, Q9049-89d3afcc-489f-762e-9bd7-cbb9ff0ec7f7)": {
            "Noam Chomsky-political ideology-anarcho-syndicalism": [
                "Noam Chomsky's political ideology is anarcho-syndicalism.",
                "Noam Chomsky advocates for an anarcho-syndicalism."
            ]
        },
        "(Q9049, P1142, Q9049-baf699e1-4236-c176-f095-7487a6736947)": {
            "Noam Chomsky-political ideology-libertarian socialism": [
                "Noam Chomsky's political ideology is libertarian socialism.",
                "Noam Chomsky advocates for a libertarian socialism."
            ]
        }
    },
    {
        "(Q9049, P1343, Q9049-000D595C-34E2-4EEF-902B-5D25EB286F5F)": {
            "Noam Chomsky-described by source-Armenian Soviet Encyclopedia": [
                "Noam Chomsky is described by the source Armenian Soviet Encyclopedia.",
                "The Armenian Soviet Encyclopedia includes descriptions of Noam Chomsky."
            ]
        },
        "(Q9049, P1343, Q9049-23BA23D9-822F-4961-A73F-5067A0F87B1D)": {
            "Noam Chomsky-described by source-Medvik": [
                "Noam Chomsky is described by the source Medvik.",
                "The Medvik includes descriptions of Noam Chomsky."
            ]
        }
    },
    {
        "(Q9049, P135, Q9049-2B327B7F-3379-450B-AF41-AD00578FD093)": {
            "Noam Chomsky-movement-atheism": [
                "Noam Chomsky is associated with the atheism movement.",
                "-"
            ]
        },
        "(Q9049, P135, Q9049-4130192d-4b61-166a-3e16-e9cfed275410)": {
            "Noam Chomsky-movement-anarcho-syndicalism": [
                "Noam Chomsky is associated with the anarcho-syndicalism movement.",
                "-"
            ]
        },
        "(Q9049, P135, Q9049-cf31a2aa-454e-53e7-d5cc-8854c9f99541)": {
            "Noam Chomsky-movement-anti-war movement": [
                "Noam Chomsky is associated with the anti-war movement.",
                "-"
            ]
        },
        "(Q9049, P135, Q9049-ed33aae1-4f17-741e-92b8-a5dc74862e85)": {
            "Noam Chomsky-movement-New Left": [
                "Noam Chomsky is associated with the New Left movement.",
                "-"
            ]
        }
    },
    {
        "(Q9049, P19, Q9049-835A41E5-8289-4075-A9A3-31F93F0CC69A)": {
            "Noam Chomsky-place of birth-Philadelphia:located in the administrative territorial entity-Pennsylvania": [
                "Noam Chomsky's place of birth is Philadelphia, which is located in the administrative territorial entity of Pennsylvania.",
                "Noam Chomsky was born in Philadelphia, located in Pennsylvania."
            ]
        }
    },
    {
        "(Q9049, P2021, Q9049-0A018FE4-557F-4A00-AF46-AFA8238D39E7)": {
            "Noam Chomsky-Erdős number": [
                "Noam Chomsky's Erdős number is 4.",
                "Noam Chomsky has an Erdős number of 4."
            ]
        }
    },
    {
        "(Q9049, P2348, Q9049-3357c102-4ab3-e822-9222-d1b5f216cf09)": {
            "Noam Chomsky-time period-contemporary philosophy": [
                "Noam Chomsky's work falls within the time period of contemporary philosophy.",
                "-"
            ]
        }
    },
    {
        "(Q9049, P26, Q9049-1CE8AA5A-5001-407D-987B-A2D96AF9BE0B)": {
            "Noam Chomsky-spouse-Carol Chomsky:end cause-death of subject's spouse": [
                "Noam Chomsky's spouse is Carol Chomsky, who passed away.",
                "-"
            ]
        },
        "(Q9049, P27, Q9049-144C2B20-875C-4DCA-8023-71BF61FB710A)": {
            "Noam Chomsky-country of citizenship-United States of America": [
                "Noam Chomsky's country of citizenship is the United States of America.",
                "Noam Chomsky is an American."
            ]
        },
        "(Q9049, P39, Q9049-8da2d4e1-9c6c-416c-931d-f073a5c06d2d)": {
            "Noam Chomsky-position held-professor": [
                "Noam Chomsky's is a professor.",
                "Noam Chomsky holds the position of a professor."
            ]
        },
        "(Q9049, P40, Q9049-472ab1a5-4265-3e64-6a96-0e3bdf13cf2a)": {
            "Noam Chomsky-child-Aviva Chomsky": [
                "Aviva Chomsky is a child of Noam Chomsky.",
                "Noam Chomsky's child is Aviva Chomsky."
            ]
        },
        "(Q9049, P463, Q9049-0EEA9C9B-35B6-4B1E-842A-C05E536BBAE6)": {
            "Noam Chomsky-member of-German Academy of Sciences Leopoldina": [
                "Noam Chomsky is a member of the German Academy of Sciences Leopoldina.",
                "Noam Chomsky holds membership in the German Academy of Sciences Leopoldina."
            ]
        },
        "(Q9049, P463, Q9049-1601673D-0764-446A-9267-77DB95B80FD7)": {
            "Noam Chomsky-member of-American Association for the Advancement of Science": [
                "Noam Chomsky is a member of the American Association for the Advancement of Science.",
                "Noam Chomsky holds membership in the American Association for the Advancement of Science."
            ]
        },
        "(Q9049, P463, Q9049-46980D46-538D-4E9D-BE45-E29A0C5983F4)": {
            "Noam Chomsky-member of-American Philosophical Society": [
                "Noam Chomsky is a member of the American Philosophical Society.",
                "Noam Chomsky holds membership in the American Philosophical Society."
            ]
        },
        "(Q9049, P512, q9049-ccd29178-43bd-c065-39b5-3f46747b7f66)": {
            "Noam Chomsky-academic degree-Doctor of Philosophy:educated at-University of Pennsylvania": [
                "Noam Chomsky has an academic degree of Doctor of Philosophy from the University of Pennsylvania.",
                "-"
            ]
        },
        "(Q9049, P551, Q9049-FBFB6D3B-54AE-49ED-9947-CF4F708E2D3E)": {
            "Noam Chomsky-residence-Tucson": [
                "Noam Chomsky resides in Tucson.",
                "Noam Chomsky's residence is in Tucson."
            ]
        },
        "(Q9049, P569, q9049-35B91161-A5E7-4DC7-A25A-193D30E78831)": {
            "Noam Chomsky-date of birth:1928-12-07T00:00:00Z": [
                "Noam Chomsky's date of birth is December 7, 1928.",
                "Noam Chomsky was born on December 7, 1928."
            ]
        }
    },
    {
        "(Q56898, P156, Q56898-ae0945a7-455a-f03f-6b38-37d5456d3be3)": {
            "Wii Remote-followed by-Wii U Pro Controller:": [
                "The Wii U Pro Controller is releazed after the Wii Remote.",
                "The Wii Remote is releazed before the Wii U Pro Controller."
            ]
        }
    },
    {
        "(Q56898, P17, Q56898-ff561a5c-4880-9b18-7dc0-b03c40ba2553)": {
            "Wii Remote-country-Japan": [
                "The Wii Remote's country is Japan.",
                "The Wii Remote country of orgin is Japan."
            ]
        }
    },
    {
        "(Q1987090, P17, Q1987090-C05F89A2-5314-4055-AC36-0BAD4553F991)": {
            "economy of Egypt-country-Egypt": [
                "The economy of Egypt pertains to Egypt.",
                "The country associated with the economy of Egypt is Egypt."
            ]
        }
    },
    {
        "(Q105612231, P1082, Q105612231-9b295c08-498d-b241-4f96-e1ada64eab47)": {
            "United Airlines Flight 328-population": [
                "The population of United Airlines Flight 328 is 241.",
                "There were 241 passengers on United Airlines Flight 328."
            ]
        }
    },
    {
        "(Q105612231, P1120, Q105612231-d45baa92-4e6d-beb5-9c0b-bb9ef6d03a4d)": {
            "United Airlines Flight 328-number of deaths": [
                "The number of deaths in United Airlines Flight 328 is 0.",
                "United Airlines Flight 328 accendent resulted in no fatalities."
            ]
        }
    },
    {
        "(Q105612231, P17, Q105612231-65b6cd2b-49bf-30c4-87d9-b5aade7616cc)": {
            "United Airlines Flight 328-country-United States of America-:-": [
                "The country of United Airlines Flight 328 is United States of America.",
                "United Airlines Flight 328 accendent occured in the United States of America."
            ]
        }
    },
    {
        "(Q1000479, P17, q1000479-97B5274E-7C0F-4F7D-A7E5-449106E40FFA)": {
            "Boston Children's Hospital-country-United States of America": [
                "The country of Boston Children's Hospital is United States of America.",
                "Boston Children's Hospital is located in the United States of America."
            ]
        }
    },
    {
        "(Q5705, P1082, Q5705-8a55fc21-488d-a3da-d811-f4d94548694f)": {
            "Catalonia-population-7424754:point in time-1 January 2015": [
                "The population of Catalonia was 7424754 on 1 January 2015.",
                "-"
            ]
        }
    }
]